{
    "search_metadata": {
        "id": "6895378313f4b65ffee0d4bb",
        "status": "Success",
        "json_endpoint": "https://serpapi.com/searches/12319e5b71282ac6/6895378313f4b65ffee0d4bb.json",
        "created_at": "2025-08-07 23:32:19 UTC",
        "processed_at": "2025-08-07 23:32:19 UTC",
        "google_maps_reviews_url": "https://www.google.com/maps/place/data=!4m7!3m6!1s!5m2!4m1!1i2!9m1!1b1?hl=en&gl=",
        "raw_html_file": "https://serpapi.com/searches/12319e5b71282ac6/6895378313f4b65ffee0d4bb.html",
        "prettify_html_file": "https://serpapi.com/searches/12319e5b71282ac6/6895378313f4b65ffee0d4bb.prettify",
        "total_time_taken": 0.73
    },
    "search_parameters": {
        "engine": "google_maps_reviews",
        "place_id": "ChIJn4ii2YCOGGARnj3-PUaZ_Qg",
        "hl": "en",
        "next_page_token": "CAESY0NBRVFIQnBFUTJwRlNVRlNTWEJEWjI5QlVEY3lSMnROZDBwaWQxOWZSV2hCTlRjNGJuUXRSMnhzYjNSUGJsQnpTVUZCUVVGQlIyZHVPVEpXWTBOaFVYcEJiSFpCV1VGRFNVRQ==",
        "num": "20",
        "sort_by": "newestFirst"
    },
    "reviews": [
        {
            "link": "https://www.google.com/maps/reviews/data=!4m8!14m7!1m6!2m5!1sChdDSUhNMG9nS0VNbWdwYXlRZ2QzbTl3RRAB!2m1!1s0x0:0x8fd99463dfe3d9e!3m1!1s2@1:CIHM0ogKEMmgpayQgd3m9wE%7CCgwIzZKowQYQiIyjmAM%7C?hl=en",
            "rating": 5.0,
            "date": "2 months ago",
            "iso_date": "2025-05-18T16:22:37Z",
            "iso_date_of_last_edit": "2025-05-18T16:22:37Z",
            "source": "Google",
            "review_id": "ChdDSUhNMG9nS0VNbWdwYXlRZ2QzbTl3RRAB",
            "user": {
                "name": "Jobir Jasurov",
                "link": "https://www.google.com/maps/contrib/106618650075330187462?hl=en",
                "contributor_id": "106618650075330187462",
                "thumbnail": "https://lh3.googleusercontent.com/a/ACg8ocK0HgXMOeieLDBFJ5nqRk_24jyVWOPRxNc2FvHzl1KpMVTbNg=s120-c-rp-mo-br100",
                "local_guide": true,
                "reviews": 2,
                "photos": 0
            },
            "snippet": "Juda hush muomila insonlar xizmat ko\u02bbrsatadi. Va ovqatlari juda yoqimli",
            "extracted_snippet": {
                "original": "Juda hush muomila insonlar xizmat ko\u02bbrsatadi. Va ovqatlari juda yoqimli",
                "translated": "Very friendly people serve. And the food is very delicious."
            },
            "details": {
                "meal_type": "Lunch",
                "price_per_person": "\u00a52,000\u20133,000",
                "food": 5,
                "service": 5,
                "atmosphere": 5,
                "recommended_dishes": "\u0423\u0437\u0431\u0435\u043a\u0441\u043a\u0430\u044f \u041b\u0435\u043f\u0435\u0448\u043a\u0430",
                "noise_level": "Quiet, easy to talk",
                "parking_space": "Plenty of parking"
            },
            "response": {
                "date": "2 months ago",
                "iso_date": "2025-05-19T06:55:46Z",
                "iso_date_of_last_edit": "2025-05-19T06:55:46Z",
                "snippet": "Katta rahmat! Yana keling kutamiz!\ud83d\udc4d",
                "extracted_snippet": {
                    "original": "Katta rahmat! Yana keling kutamiz!\ud83d\udc4d",
                    "translated": "Thank you very much! Let's wait again!\ud83d\udc4d"
                }
            }
        },
        {
            "link": "https://www.google.com/maps/reviews/data=!4m8!14m7!1m6!2m5!1sChZDSUhNMG9nS0VMNzMwdlNQLXUtSVRnEAE!2m1!1s0x0:0x8fd99463dfe3d9e!3m1!1s2@1:CIHM0ogKEL730vSP-u-ITg%7CCgwItqeXwQYQwJ3Z4AE%7C?hl=en",
            "rating": 5.0,
            "date": "2 months ago",
            "iso_date": "2025-05-15T11:44:54Z",
            "iso_date_of_last_edit": "2025-05-15T11:44:54Z",
            "images": [
                "https://lh3.googleusercontent.com/geougc-cs/AB3l90CI0CJk2BUUSU89XiCLJmeTfmp4ulpMB1BTWNTr4htwGAH-BW1w4GQMBAH99qi2UwZ8PJFePlQ3M5W4EgiUlDg9LPHxkQBq1MJIT5VtSbCfhL7AiVDyRkkPOf6R_7XSUVby8-soMw",
                "https://lh3.googleusercontent.com/geougc-cs/AB3l90ACWrVByd0W0QOCHxdlf01QfPONYtZxYO3ywHmjYetpiHoNUPMkVYfAsLGsd26b0mciFVtjSK_X4KQKwzsqEPY1GqzeG5R2dJb9xcK6zwqpoDcx_HdjKITUFJBpGi42sxwTg394GQ",
                "https://lh3.googleusercontent.com/geougc-cs/AB3l90CtwUALUNcsLyaAyCtpgb6qWvgOhYHjDesXNMJeQuMhWhvEfVpJ93GI83Xwb-ea399zgEY6au9pd-ALnIuTxON_n6Un3fIGj9lCHGpAptDHNf3YhNoUuIgLSQ-LFTgjdU_25tkjeA",
                "https://lh3.googleusercontent.com/geougc-cs/AB3l90BpsCN1Tza6DcFYF9itYAt-87YVISBhLFvAVWyahxv4KTXJOuGLjYwtZKyZQaX6RQzqdbfFwZbyaREUl-e2ganiGrCzIdTiU86Fp1zMOCNP-JN47pHyaFk93RAuh35yBczW4ZUOEQ"
            ],
            "source": "Google",
            "review_id": "ChZDSUhNMG9nS0VMNzMwdlNQLXUtSVRnEAE",
            "user": {
                "name": "Mustafa Emal",
                "link": "https://www.google.com/maps/contrib/102151011354382348332?hl=en",
                "contributor_id": "102151011354382348332",
                "thumbnail": "https://lh3.googleusercontent.com/a/ACg8ocIn5kKEBMaIceL5bLNGK_5SKTV_ERdD0iHWUknnX44WfqE_Kik=s120-c-rp-mo-br100",
                "local_guide": true,
                "reviews": 7,
                "photos": 9
            },
            "snippet": "Sakura is a true gem \ud83d\udc8e in Tokyo!\nEvery aspect of my experience was perfect-from the warm, family-run atmosphere to the authentic Uzbek dishes bursting with flavor \ud83d\ude0b. The plov, shashlik, samosa, shorva, etc. were outstanding \ud83d\ude0d, portions generous, and the service was genuinely welcoming!\n\nLazzat is an absolute a must-visit in Seoul. Highly recommended!",
            "extracted_snippet": {
                "original": "Sakura is a true gem \ud83d\udc8e in Tokyo!\nEvery aspect of my experience was perfect-from the warm, family-run atmosphere to the authentic Uzbek dishes bursting with flavor \ud83d\ude0b. The plov, shashlik, samosa, shorva, etc. were outstanding \ud83d\ude0d, portions generous, and the service was genuinely welcoming!\n\nLazzat is an absolute a must-visit in Seoul. Highly recommended!"
            },
            "details": {
                "meal_type": "Dinner",
                "price_per_person": "\u00a52,000\u20133,000",
                "food": 5,
                "service": 5,
                "atmosphere": 5,
                "group_size": "Suitable for all group sizes",
                "wait_time": "No wait"
            },
            "response": {
                "date": "2 months ago",
                "iso_date": "2025-05-15T13:25:04Z",
                "iso_date_of_last_edit": "2025-05-15T13:25:04Z",
                "snippet": "Thank you so much for your heartwarming review!\nYour kind words mean a lot to our team.\nWe look forward to serving you again soon!",
                "extracted_snippet": {
                    "original": "Thank you so much for your heartwarming review!\nYour kind words mean a lot to our team.\nWe look forward to serving you again soon!"
                }
            }
        },
        {
            "link": "https://www.google.com/maps/reviews/data=!4m8!14m7!1m6!2m5!1sChdDSUhNMG9nS0VKeU45UHJfbVplLWdnRRAB!2m1!1s0x0:0x8fd99463dfe3d9e!3m1!1s2@1:CIHM0ogKEJyN9Pr_mZe-ggE%7CCgsI2fKBwQYQ-IrVaQ%7C?hl=en",
            "rating": 5.0,
            "date": "2 months ago",
            "iso_date": "2025-05-11T10:04:25Z",
            "iso_date_of_last_edit": "2025-05-11T10:18:01Z",
            "images": [
                "https://lh3.googleusercontent.com/geougc-cs/AB3l90C16Wt3wdwgUI6cAZesahG1g-O2LaASLKHFzkmlSIEeUEhNi37FvDW085ciyW9RegM-gYhNZYIdzSrtJA1UMGHz8BBoqbGQXhrbiYi6jJK7h4NlxLbOm7LxBRINnP38CacestrGPA",
                "https://lh3.googleusercontent.com/geougc-cs/AB3l90BXhZtX6yV8HfWfkuWXYYIYKU__GGWWbhg2S4tflFFOQIWKhYLB0pLBipjLHrzvPS-bDWNzbMNFI7OkwcBlsz4oVRICqnEO2OepC5yNQHg2iQIMJaa9uyg2nRNY1W8skq6JPl-m",
                "https://lh3.googleusercontent.com/geougc-cs/AB3l90A10yOoNMR6XUWjA44V03EOyqY5tSixwFp-AeCl4OtGZPB_SgYTTQy1HxAf8_lVPsR66sPRrax7swBD9jHHekQMoAGOCz1wO08OFiscvtkBJdixQJvAOXhyI7SJhVgeb7EZ042U",
                "https://lh3.googleusercontent.com/geougc-cs/AB3l90AGmT9_RIbFBCOiiWBjUtt2vHYoLYJUVuBJFjJZVUk79HxAp_LGJxbz_DMam2hl_NlW_vg-fdHZT1DvIzFP6CWeiuzuhbcEGi409x-tvqrf0wiXTZViKAdqx5DGlLQl1UsMFNKZqg"
            ],
            "source": "Google",
            "review_id": "ChdDSUhNMG9nS0VKeU45UHJfbVplLWdnRRAB",
            "user": {
                "name": "ha zar",
                "link": "https://www.google.com/maps/contrib/100238369328212004837?hl=en",
                "contributor_id": "100238369328212004837",
                "thumbnail": "https://lh3.googleusercontent.com/a/ACg8ocKyW1DSFC4QlvuUMUxnPhCi5gOxVlISTutjC9P7tdqtCFcmRQ=s120-c-rp-mo-ba2-br100",
                "local_guide": true,
                "reviews": 23,
                "photos": 5
            },
            "snippet": "Was man im Vergleich hier in Tokio zahlt, absolut faire Preise.\nDirekt vor der T\u00fcr gibt es eine Haltestelle. Top erreichbar.\nEs gibt auch einen ger\u00e4umigen Gebetsraum.\nEssen schmeckt unglaublich gut. Absolute empfehlung.",
            "extracted_snippet": {
                "original": "Was man im Vergleich hier in Tokio zahlt, absolut faire Preise.\nDirekt vor der T\u00fcr gibt es eine Haltestelle. Top erreichbar.\nEs gibt auch einen ger\u00e4umigen Gebetsraum.\nEssen schmeckt unglaublich gut. Absolute empfehlung.",
                "translated": "What you pay in comparison here in Tokyo, absolutely fair prices.\nThere is a stop right in front of the door. Very accessible.\nThere is also a spacious prayer room.\nFood tastes incredibly good. Absolute recommendation."
            },
            "details": {
                "meal_type": "Dinner",
                "price_per_person": "\u00a52,000\u20133,000",
                "food": 5,
                "service": 5,
                "atmosphere": 5,
                "noise_level": "Quiet, easy to talk",
                "wait_time": "No wait"
            },
            "response": {
                "date": "2 months ago",
                "iso_date": "2025-05-13T14:44:33Z",
                "iso_date_of_last_edit": "2025-05-13T14:44:33Z",
                "snippet": "Thank you very much for your wonderful feedback!\nWe truly appreciate your recommendation and look forward to seeing you again!",
                "extracted_snippet": {
                    "original": "Thank you very much for your wonderful feedback!\nWe truly appreciate your recommendation and look forward to seeing you again!"
                }
            }
        },
        {
            "link": "https://www.google.com/maps/reviews/data=!4m8!14m7!1m6!2m5!1sChZDSUhNMG9nS0VOcjc2YnVrbmYtNENREAE!2m1!1s0x0:0x8fd99463dfe3d9e!3m1!1s2@1:CIHM0ogKENr76buknf-4CQ%7CCgsIm9nswAYQ0Lb2ew%7C?hl=en",
            "rating": 5.0,
            "date": "3 months ago",
            "iso_date": "2025-05-07T09:49:15Z",
            "iso_date_of_last_edit": "2025-05-07T09:49:15Z",
            "images": [
                "https://lh3.googleusercontent.com/geougc-cs/AB3l90A5xYueDHnTEscgZ25jY2OdMw12As1rgDVXL0pcHgAVJ9dYlWaujO9XW9mwMutJytK-3jeuWvl5wpKyjzVyYK45fQFCCuX5E6IPWSujbcC6qpUY7xbGxJUN86kYxnSgMvrdYOtydg",
                "https://lh3.googleusercontent.com/geougc-cs/AB3l90DpibTXRTvhzHLXZM6AJL7_My_31g1RBFuVpDkWR_fnDoJJUED8NZ_1ZW5Qx4NorXVSs7NNtz_7MnilBMA-9xY4wz6d-HJxDvmQlCvNf4AYf7WpOjhfzwr2TldP2Mcrr3n09fQ_wQ"
            ],
            "source": "Google",
            "review_id": "ChZDSUhNMG9nS0VOcjc2YnVrbmYtNENREAE",
            "user": {
                "name": "\u30ce\u30e8\u30ea\u6c99\u6075\u826f",
                "link": "https://www.google.com/maps/contrib/100013576143694904139?hl=en",
                "contributor_id": "100013576143694904139",
                "thumbnail": "https://lh3.googleusercontent.com/a-/ALV-UjWLyVGUKvchx-XlBXFi5dZEVlEG4sTCGg0M1GdxenG6Q1elW9tY=s120-c-rp-mo-ba2-br100",
                "local_guide": true,
                "reviews": 20,
                "photos": 21
            },
            "snippet": "\u30c1\u30a7\u30ea\u30fc\u30b8\u30e5\u30fc\u30b9\u3068\u5358\u54c1\u306e\u30b1\u30d0\u30d6\u3068\u30d7\u30ed\u30d6\u30bb\u30c3\u30c8\u3092\u983c\u307f\u307e\u3057\u305f\ud83c\udf52\n\u3069\u308c\u3082\u3068\u3066\u3082\u7f8e\u5473\u3057\u304b\u3063\u305f\u3067\u3059\u2728\n\u98df\u3079\u5fdc\u3048\u304c\u3042\u3063\u3066\u6700\u9ad8\u3067\u3057\u305f\ud83c\udf56",
            "extracted_snippet": {
                "original": "\u30c1\u30a7\u30ea\u30fc\u30b8\u30e5\u30fc\u30b9\u3068\u5358\u54c1\u306e\u30b1\u30d0\u30d6\u3068\u30d7\u30ed\u30d6\u30bb\u30c3\u30c8\u3092\u983c\u307f\u307e\u3057\u305f\ud83c\udf52\n\u3069\u308c\u3082\u3068\u3066\u3082\u7f8e\u5473\u3057\u304b\u3063\u305f\u3067\u3059\u2728\n\u98df\u3079\u5fdc\u3048\u304c\u3042\u3063\u3066\u6700\u9ad8\u3067\u3057\u305f\ud83c\udf56",
                "translated": "I ordered cherry juice and a kebab and plov set\ud83c\udf52\nEverything was very delicious \u2728\nIt was delicious and filling\ud83c\udf56"
            },
            "details": {
                "price_per_person": "\u00a52,000\u20133,000",
                "food": 5,
                "service": 5,
                "atmosphere": 5,
                "group_size": "1 person",
                "special_events": "No special event",
                "wait_time": "No wait"
            },
            "response": {
                "date": "2 months ago",
                "iso_date": "2025-05-09T19:24:23Z",
                "iso_date_of_last_edit": "2025-05-09T19:24:23Z",
                "snippet": "\u7d20\u6575\u306a\u30ec\u30d3\u30e5\u30fc\u3042\u308a\u304c\u3068\u3046\u3054\u3056\u3044\u307e\u3059\uff01\u307e\u305f\u306e\u3054\u6765\u5e97\u3092\u5fc3\u3088\u308a\u304a\u5f85\u3061\u3057\u3066\u304a\u308a\u307e\u3059\u3002\ud83d\udc4f",
                "extracted_snippet": {
                    "original": "\u7d20\u6575\u306a\u30ec\u30d3\u30e5\u30fc\u3042\u308a\u304c\u3068\u3046\u3054\u3056\u3044\u307e\u3059\uff01\u307e\u305f\u306e\u3054\u6765\u5e97\u3092\u5fc3\u3088\u308a\u304a\u5f85\u3061\u3057\u3066\u304a\u308a\u307e\u3059\u3002\ud83d\udc4f",
                    "translated": "Thank you for the wonderful review! We look forward to seeing you again. \ud83d\udc4f"
                }
            }
        },
        {
            "link": "https://www.google.com/maps/reviews/data=!4m8!14m7!1m6!2m5!1sChZDSUhNMG9nS0VQTF9zS180OXJ6MkxnEAE!2m1!1s0x0:0x8fd99463dfe3d9e!3m1!1s2@1:CIHM0ogKEPL_sK_49rz2Lg%7CCgwIqa_nwAYQiJrCoAE%7C?hl=en",
            "rating": 5.0,
            "date": "3 months ago",
            "iso_date": "2025-05-06T09:34:33Z",
            "iso_date_of_last_edit": "2025-05-06T09:34:33Z",
            "images": [
                "https://lh3.googleusercontent.com/geougc-cs/AB3l90C9QPbZerlAucQUZwkOqrq-E9ztxxXKMW17Nv_eHtv_oA1aqxE8nKGodOsjwQh5MAHW9brH2Z-2IeRhqH00W_29WlZ5yV5tBZ9Q2LLrDgHYgwE_sVS3Q1DJH6bYRwtylK1abtuy",
                "https://lh3.googleusercontent.com/geougc-cs/AB3l90C2f4xFR0U7PkqcRZQ3wrFqlyGZ87FapVFn3J1Zr35S9lEA7dZTVLAMVLXYVgcvrdi_0cW7Pqx2EY0H4O2h8hEmBsfdDAoBFr5v6EcEaB-MmgF1sjC62YuWhFaTIGjpioltvbSamg"
            ],
            "source": "Google",
            "review_id": "ChZDSUhNMG9nS0VQTF9zS180OXJ6MkxnEAE",
            "user": {
                "name": "R.fauziah Ismail",
                "link": "https://www.google.com/maps/contrib/104265422215758614831?hl=en",
                "contributor_id": "104265422215758614831",
                "thumbnail": "https://lh3.googleusercontent.com/a-/ALV-UjXL5zqpZ_wOtvwF6WAi29RW7AOHVPrvdgH-Zd9zqrs9kq61ppeEWw=s120-c-rp-mo-ba2-br100",
                "local_guide": true,
                "reviews": 23,
                "photos": 15
            },
            "snippet": "Super delicious food..Halal is important..Price Affordable \ud83d\udc4d\nThank You so much \ud83d\ude4f",
            "extracted_snippet": {
                "original": "Super delicious food..Halal is important..Price Affordable \ud83d\udc4d\nThank You so much \ud83d\ude4f"
            },
            "details": {
                "food": 5,
                "service": 5,
                "atmosphere": 5
            },
            "response": {
                "date": "2 months ago",
                "iso_date": "2025-05-09T19:27:41Z",
                "iso_date_of_last_edit": "2025-05-09T19:27:41Z",
                "snippet": "Thank you so much for your kind words!\nWe\u2019re happy you enjoyed the food and appreciated our halal offerings at an affordable price.\ud83d\udc4f\nHope to welcome you again soon!",
                "extracted_snippet": {
                    "original": "Thank you so much for your kind words!\nWe\u2019re happy you enjoyed the food and appreciated our halal offerings at an affordable price.\ud83d\udc4f\nHope to welcome you again soon!"
                }
            }
        },
        {
            "link": "https://www.google.com/maps/reviews/data=!4m8!14m7!1m6!2m5!1sChZDSUhNMG9nS0VMR1dySjMzb3NHTWF3EAE!2m1!1s0x0:0x8fd99463dfe3d9e!3m1!1s2@1:CIHM0ogKELGWrJ33osGMaw%7CCgwIu93lwAYQsNS79wE%7C?hl=en",
            "rating": 5.0,
            "date": "3 months ago",
            "iso_date": "2025-05-06T02:06:51Z",
            "iso_date_of_last_edit": "2025-05-06T02:06:51Z",
            "images": [
                "https://lh3.googleusercontent.com/geougc-cs/AB3l90Bq-wfnXUbuRDfpO5EKoAi8_V1NSa7ghg17zJAicoQqLyK-p-uuUZrjYGKKTEdnd997kFdxmuPa89-_PWMlpe2sEAtBaa14zEC0JjCqXYc0vaO036GZW-eOxwTaEeWThAKkoUis",
                "https://lh3.googleusercontent.com/geougc-cs/AB3l90DRmI7pIsfGt0zk5aEsleTgSlPegXSgtzzsK3QPTjsD1-1A6nZ_fz9olcrwm4v0xROYqqvAcva8vdn5ZQdx2r5iC-__gyWh0aVivtBN-cP59ewhZFPxlpjK4c-8odM94iLOUS6A",
                "https://lh3.googleusercontent.com/geougc-cs/AB3l90DPB8p8ec7h_Eol14FzmqUs88nmBOcJ-Z7-v7xtkg4IXlXlchjHBEzSFRziK33VvP95WnrXPJYaxhBQL-w8Ze9G3eu_QQ2M0is8sWF9omgNwRp-Oh7V7YOOyNGf-QphbQjKsXpt",
                "https://lh3.googleusercontent.com/geougc-cs/AB3l90C0p-IB9Tl6XqVXL0iVV1kqHRpm2rHY3Enxb3CMSVK0zPl-gTiB2NT6B7wr54WmFo5H9Bdo5HuliCAewYhlj7Me01VQCnnScmacReZ3G_6UjVO7JEBY3A2H-wJ6gZPx6jDuHhjh"
            ],
            "source": "Google",
            "review_id": "ChZDSUhNMG9nS0VMR1dySjMzb3NHTWF3EAE",
            "user": {
                "name": "Tani Zaki",
                "link": "https://www.google.com/maps/contrib/113950733955658387791?hl=en",
                "contributor_id": "113950733955658387791",
                "thumbnail": "https://lh3.googleusercontent.com/a/ACg8ocLHtV6gqaIlr1iev2u_Fm8bvddi72wPIpj9QHo4nT8m1n3y1w=s120-c-rp-mo-ba6-br100",
                "local_guide": true,
                "reviews": 100,
                "photos": 3120
            },
            "details": {
                "meal_type": "Lunch",
                "price_per_person": "\u00a51,000\u20132,000",
                "food": 5,
                "service": 4,
                "atmosphere": 4
            },
            "response": {
                "date": "2 months ago",
                "iso_date": "2025-05-09T19:28:21Z",
                "iso_date_of_last_edit": "2025-05-09T19:28:21Z",
                "snippet": "Thank you so much!",
                "extracted_snippet": {
                    "original": "Thank you so much!"
                }
            }
        },
        {
            "link": "https://www.google.com/maps/reviews/data=!4m8!14m7!1m6!2m5!1sChdDSUhNMG9nS0VJQ0FnTUNZeXRmRTBBRRAB!2m1!1s0x0:0x8fd99463dfe3d9e!3m1!1s2@1:CIHM0ogKEICAgMCYytfE0AE%7CCgwIv83XwAYQ0LuFqwI%7C?hl=en",
            "rating": 5.0,
            "date": "3 months ago",
            "iso_date": "2025-05-03T09:49:51Z",
            "iso_date_of_last_edit": "2025-05-03T09:49:51Z",
            "images": [
                "https://lh3.googleusercontent.com/geougc-cs/AB3l90DOokXqEwpwosJ0n3uKVmJ-fDe2zHL_T4wvnFlfOsdyRL7zukuVUb8AKcK0gRlAEKHby45CdZH8IufGkXPD0vC0brD8wdRGWhiwCJ3KqL-fA-ffuJLJmSJ08J__XpcqLh97ETgQ",
                "https://lh3.googleusercontent.com/geougc-cs/AB3l90CsRMlzlukHsqjd7E9KedRaifkh1kVoBOKX73rTUqml80vur6No7Tetq6aWmL66dRah-vGCB0gWngzqN-867Hhj7rknhnKzg7w3wFaCNBELHyqO0lYuLgv8K-J7Fs0X9cGyBABnvg",
                "https://lh3.googleusercontent.com/geougc-cs/AB3l90CjXf5_yjX1YnybI8SwYoF0SHVBnAvBrdwaJ1zBU6qxVWHAYoI-l50YMcTvUL8AFHErTzfBd9wT_N_YJhHXieRL_l52MQN4oTgrDyAHR563PT3Uwq15S9pi6PFbwUf2EaAv4YXj"
            ],
            "source": "Google",
            "review_id": "ChdDSUhNMG9nS0VJQ0FnTUNZeXRmRTBBRRAB",
            "user": {
                "name": "Sibel Ysk",
                "link": "https://www.google.com/maps/contrib/102801636027055327885?hl=en",
                "contributor_id": "102801636027055327885",
                "thumbnail": "https://lh3.googleusercontent.com/a-/ALV-UjWAqTMfubFtoEPP2wjiRgkiHcw51ZhQpGhspidTO-DNaFgeelS9=s120-c-rp-mo-br100",
                "local_guide": true,
                "reviews": 5,
                "photos": 3
            },
            "snippet": "All food is delicious. Highly recommended",
            "extracted_snippet": {
                "original": "All food is delicious. Highly recommended"
            },
            "details": {
                "food": 5,
                "service": 5,
                "atmosphere": 5
            },
            "response": {
                "date": "3 months ago",
                "iso_date": "2025-05-03T11:16:38Z",
                "iso_date_of_last_edit": "2025-05-03T11:16:38Z",
                "snippet": "Thank you so much \ud83d\udc4f",
                "extracted_snippet": {
                    "original": "Thank you so much \ud83d\udc4f"
                }
            }
        },
        {
            "link": "https://www.google.com/maps/reviews/data=!4m8!14m7!1m6!2m5!1sChZDSUhNMG9nS0VJQ0FnTUNZaEtDZ2VBEAE!2m1!1s0x0:0x8fd99463dfe3d9e!3m1!1s2@1:CIHM0ogKEICAgMCYhKCgeA%7CCgwIj9HNwAYQ-MflyQI%7C?hl=en",
            "rating": 5.0,
            "date": "3 months ago",
            "iso_date": "2025-05-01T08:30:06Z",
            "iso_date_of_last_edit": "2025-05-01T12:26:55Z",
            "images": [
                "https://lh3.googleusercontent.com/geougc-cs/AB3l90Bttdv1ewGl3WhR1FpHR61tE-4m_mnVWoGYiX0LDLseBmKG2whfkPPcn1Nlth4sqG4Yb7leTZQBDNAixCUpH7wGt-HbNR7KcWqZYN6PGNOhmu-kjAxI_33Scqdpui8oNnctvf5I",
                "https://lh3.googleusercontent.com/geougc-cs/AB3l90DN9sjqWpP4qO6EvqOZSNNe1GN3b7VXdR1PO2UwtcPPAm75VF4qBvmgmBfDOTGIxJCH9gFjm11C7FtS0JPEnqDNur4i3fiuwgS_rgOrPT2bbzSMZ3fFjQt-WKL97zmfVtOreKekSQ",
                "https://lh3.googleusercontent.com/geougc-cs/AB3l90BZ3ldvYPE-Dkk4n8gjmkAMiFar3-HTwablhC8TYohDQt9NVt-n8I_zTlpHlJjM5VfKBVLt-aWUcCxyYT9ECewrC7TSitiiQ7z0eleX7J3Rd2Bb1w2BXqCJxc0Ft7QTaDJM4Ws",
                "https://lh3.googleusercontent.com/geougc-cs/AB3l90BmdGximhWbB14BPslz-Iu2epSpnWAJXaetzvZvqV9PIMshBTvhE6KJ_VXZYAggDxEGAfVXfVmjMm9KYeJwdMV15rwt2tGX9edN1ULteBrTwX1dzAPRCF3ekeUxTqEs7Dgd_DF-hA"
            ],
            "source": "Google",
            "review_id": "ChZDSUhNMG9nS0VJQ0FnTUNZaEtDZ2VBEAE",
            "user": {
                "name": "Kamil Rauf (Kam)",
                "link": "https://www.google.com/maps/contrib/108341015333267652652?hl=en",
                "contributor_id": "108341015333267652652",
                "thumbnail": "https://lh3.googleusercontent.com/a-/ALV-UjW_mVyL6_JM27U_h6rVFsASwIdRpUzd7X_18ckaK1EOsORkCrhKxg=s120-c-rp-mo-br100",
                "local_guide": true,
                "reviews": 7,
                "photos": 5
            },
            "snippet": "As someone who\u2019s had kebabs across the Middle East, Europe and beyond, I can confidently say Halal Sakura in Tokyo offers something refreshingly unique. The kebab here has its own signature flavour\u2014succulent, well-spiced, and served with a side of surprise: chopsticks! First time eating kebab this way, and it actually made the whole experience even more memorable. The Central Asian twist adds depth to the usual kebab fare, and it works brilliantly.\n\nBonus points for the clean and accessible prayer space upstairs, which is such a thoughtful touch for Muslim travellers. If you\u2019re in Tokyo and craving halal comfort food with a twist, this spot is a must.",
            "extracted_snippet": {
                "original": "As someone who\u2019s had kebabs across the Middle East, Europe and beyond, I can confidently say Halal Sakura in Tokyo offers something refreshingly unique. The kebab here has its own signature flavour\u2014succulent, well-spiced, and served with a side of surprise: chopsticks! First time eating kebab this way, and it actually made the whole experience even more memorable. The Central Asian twist adds depth to the usual kebab fare, and it works brilliantly.\n\nBonus points for the clean and accessible prayer space upstairs, which is such a thoughtful touch for Muslim travellers. If you\u2019re in Tokyo and craving halal comfort food with a twist, this spot is a must."
            },
            "details": {
                "price_per_person": "\u00a51,000\u20132,000",
                "food": 5,
                "service": 5,
                "atmosphere": 5,
                "noise_level": "Quiet, easy to talk",
                "group_size": "3-4 people",
                "wait_time": "No wait"
            },
            "response": {
                "date": "3 months ago",
                "iso_date": "2025-05-01T12:21:54Z",
                "iso_date_of_last_edit": "2025-05-01T12:21:54Z",
                "snippet": "Thank you so much for your thoughtful and beautifully written review! We're truly honored to hear that our kebabs stood out among your global experiences, and that you enjoyed the unique twist we offer. Your kind words mean a lot to our team\u2014hope to welcome you back again soon! ",
                "extracted_snippet": {
                    "original": "Thank you so much for your thoughtful and beautifully written review! We're truly honored to hear that our kebabs stood out among your global experiences, and that you enjoyed the unique twist we offer. Your kind words mean a lot to our team\u2014hope to welcome you back again soon! "
                }
            }
        },
        {
            "link": "https://www.google.com/maps/reviews/data=!4m8!14m7!1m6!2m5!1sChdDSUhNMG9nS0VJQ0FnTURvejlUMTNnRRAB!2m1!1s0x0:0x8fd99463dfe3d9e!3m1!1s2@1:CIHM0ogKEICAgMDoz9T13gE%7CCgsI7NvFwAYQ8PKrdQ%7C?hl=en",
            "rating": 4.0,
            "date": "3 months ago",
            "iso_date": "2025-04-30T00:25:16Z",
            "iso_date_of_last_edit": "2025-04-30T00:25:16Z",
            "source": "Google",
            "review_id": "ChdDSUhNMG9nS0VJQ0FnTURvejlUMTNnRRAB",
            "user": {
                "name": "tricks & techniques",
                "link": "https://www.google.com/maps/contrib/108681352158419742487?hl=en",
                "contributor_id": "108681352158419742487",
                "thumbnail": "https://lh3.googleusercontent.com/a-/ALV-UjWw6zr_PohdqeDcQdiuJnIMXulSuSE_GfSwQXBbVvhMP-e8O0Q=s120-c-rp-mo-br100",
                "local_guide": true,
                "reviews": 0,
                "photos": 22
            },
            "details": {
                "service": 4,
                "meal_type": "Dinner",
                "price_per_person": "\u00a51,000\u20132,000",
                "food": 4,
                "atmosphere": 5,
                "recommended_dishes": "Beef Noodles"
            },
            "response": {
                "date": "3 months ago",
                "iso_date": "2025-05-01T12:22:31Z",
                "iso_date_of_last_edit": "2025-05-01T12:22:31Z",
                "snippet": "Thank you so much!",
                "extracted_snippet": {
                    "original": "Thank you so much!"
                }
            }
        },
        {
            "link": "https://www.google.com/maps/reviews/data=!4m8!14m7!1m6!2m5!1sChZDSUhNMG9nS0VJQ0FnTURvaWQyR1VBEAE!2m1!1s0x0:0x8fd99463dfe3d9e!3m1!1s2@1:CIHM0ogKEICAgMDoid2GUA%7CCgwIl-uxwAYQyKGMwAM%7C?hl=en",
            "rating": 5.0,
            "date": "3 months ago",
            "iso_date": "2025-04-26T05:56:39Z",
            "iso_date_of_last_edit": "2025-04-26T05:56:39Z",
            "source": "Google",
            "review_id": "ChZDSUhNMG9nS0VJQ0FnTURvaWQyR1VBEAE",
            "user": {
                "name": "fazal rehman",
                "link": "https://www.google.com/maps/contrib/101781592261950649210?hl=en",
                "contributor_id": "101781592261950649210",
                "thumbnail": "https://lh3.googleusercontent.com/a-/ALV-UjUKju5lveVfOGY9CdO2u4sPln4nPUcoau-MguZ3VCafUaY4KGxC=s120-c-rp-mo-br100",
                "local_guide": true,
                "reviews": 6,
                "photos": 0
            },
            "response": {
                "date": "3 months ago",
                "iso_date": "2025-04-27T12:20:05Z",
                "iso_date_of_last_edit": "2025-04-27T12:20:05Z",
                "snippet": "Thank you so much ",
                "extracted_snippet": {
                    "original": "Thank you so much "
                }
            }
        },
        {
            "link": "https://www.google.com/maps/reviews/data=!4m8!14m7!1m6!2m5!1sChZDSUhNMG9nS0VJQ0FnTURvcnZuUGRREAE!2m1!1s0x0:0x8fd99463dfe3d9e!3m1!1s2@1:CIHM0ogKEICAgMDorvnPdQ%7CCgwI2eOrwAYQ-J6hhgE%7C?hl=en",
            "rating": 5.0,
            "date": "3 months ago",
            "iso_date": "2025-04-25T02:22:17Z",
            "iso_date_of_last_edit": "2025-04-25T02:22:17Z",
            "source": "Google",
            "review_id": "ChZDSUhNMG9nS0VJQ0FnTURvcnZuUGRREAE",
            "user": {
                "name": "Doniyorbek Shukurov",
                "link": "https://www.google.com/maps/contrib/101516350779085766009?hl=en",
                "contributor_id": "101516350779085766009",
                "thumbnail": "https://lh3.googleusercontent.com/a/ACg8ocJWE72_MUnLIigBnSBOVOjggaBo5kcU0IZQ-DPLXudl6CC9Sw=s120-c-rp-mo-br100",
                "local_guide": true,
                "reviews": 0,
                "photos": 0
            },
            "details": {
                "food": 5,
                "service": 5,
                "atmosphere": 5
            },
            "response": {
                "date": "3 months ago",
                "iso_date": "2025-04-27T12:20:16Z",
                "iso_date_of_last_edit": "2025-04-27T12:20:16Z",
                "snippet": "Katta rahmat ",
                "extracted_snippet": {
                    "original": "Katta rahmat ",
                    "translated": "Thank you very much "
                }
            }
        },
        {
            "link": "https://www.google.com/maps/reviews/data=!4m8!14m7!1m6!2m5!1sChdDSUhNMG9nS0VJQ0FnTURvNU5lMjlBRRAB!2m1!1s0x0:0x8fd99463dfe3d9e!3m1!1s2@1:CIHM0ogKEICAgMDo5Ne29AE%7CCgwIxK6cwAYQuLSM0QM%7C?hl=en",
            "rating": 5.0,
            "date": "3 months ago",
            "iso_date": "2025-04-22T04:12:52Z",
            "iso_date_of_last_edit": "2025-04-22T04:12:52Z",
            "images": [
                "https://lh3.googleusercontent.com/geougc-cs/AB3l90BKUkoVrfgFrUFB22OE8GFJrmAZv6AvZ_QMWsGoOO3pSt6utsWIgHgvUUyGyL52-9cWfui6_NKjbc8ouFWFMbsxv8sJmaqKI6PYFRESjqshW3C3gMcUZt-yUDjQEGN5dZNv8ibk",
                "https://lh3.googleusercontent.com/geougc-cs/AB3l90A9mmfueouSMb73vCOQhf6TAJ_coHW1nXU0QcS3EbCKdXdH-gjbe4-OOdoD6EJiL47T1b4IGB68npx3idRpzvIyqPjh5ePDc9v5lbNvaUaii5lbMA8zXfA0gQB1SbN7xvc0nV6pKQ",
                "https://lh3.googleusercontent.com/geougc-cs/AB3l90B38aUDWPz3zx7p0WoD-Z2Cy0D5mZeUnKjp5fPxQ5nsWoNSOFn0dkM5gyJJPzqEfCPX_wy7TKmuLkXr9FgvXv7j9J0ZdBC9h6mwsmiIJioE-fUucI5nz6vebBJxXBYm4W6Njkag",
                "https://lh3.googleusercontent.com/geougc-cs/AB3l90DwZelkN8ngVrZ9luXOqOKnQ4NZpr-AgPgpwEMJ-t_IoL4XlwjZv2UraeAWb3IqyUnTgJJuj_XdQNBXJX09Qx_psLxJTQT2cXokfOOdHQz3EUU0XbHQ9u7q7vmNll7hceIOzZ_JoQ",
                "https://lh3.googleusercontent.com/geougc-cs/AB3l90DGv_XIFA0MHyKyptUQqoURJqoQqiibnA5n1g3EXFOEznFJ7PPxvVeB2LLk3u6qFlZQMVB_UIgM-4D3cjDNEJGFwIXYtrmYBjBtgk2LHyecyEVBdahzxEblpYsX6i0v_SNqm8I",
                "https://lh3.googleusercontent.com/geougc-cs/AB3l90DHGmQwh_62UahfF751PXUN2exEEM8z6P4YSHlCuQ_DV7ZCvDasFGzDMC4ew6b9x7tREA7TyIoRsbjT1m8kbYGSWTO30K1mdx_q2ri-XNNTS2fvsTjOrN7aFwbjiUh7FrgVElG5Aw"
            ],
            "source": "Google",
            "review_id": "ChdDSUhNMG9nS0VJQ0FnTURvNU5lMjlBRRAB",
            "user": {
                "name": "Ebrahim Vahed",
                "link": "https://www.google.com/maps/contrib/113563414866113860312?hl=en",
                "contributor_id": "113563414866113860312",
                "thumbnail": "https://lh3.googleusercontent.com/a/ACg8ocLxZ-G7WU96-sjL1eoRXomT2B4Il1Y6urANv3VZmx8ChDW3lQ=s120-c-rp-mo-ba4-br100",
                "local_guide": true,
                "reviews": 99,
                "photos": 232
            },
            "snippet": "Brilliant dining experience. Fusion foods. Great service. Great location. Try to get the seats with 360 street view.",
            "extracted_snippet": {
                "original": "Brilliant dining experience. Fusion foods. Great service. Great location. Try to get the seats with 360 street view."
            },
            "details": {
                "service": 5,
                "meal_type": "Lunch",
                "price_per_person": "\u00a52,000\u20133,000",
                "food": 5,
                "atmosphere": 5,
                "recommended_dishes": "Beef Rice Set, Chicken and Beef Kebab"
            },
            "response": {
                "date": "3 months ago",
                "iso_date": "2025-04-22T07:55:55Z",
                "iso_date_of_last_edit": "2025-04-22T07:55:55Z",
                "snippet": "Thank you so much for your kind words! ",
                "extracted_snippet": {
                    "original": "Thank you so much for your kind words! "
                }
            }
        },
        {
            "link": "https://www.google.com/maps/reviews/data=!4m8!14m7!1m6!2m5!1sChdDSUhNMG9nS0VJQ0FnTURvOE5LNHZBRRAB!2m1!1s0x0:0x8fd99463dfe3d9e!3m1!1s2@1:CIHM0ogKEICAgMDo8NK4vAE%7CCgsI_oKZwAYQ0L7nEA%7C?hl=en",
            "rating": 3.0,
            "date": "3 months ago",
            "iso_date": "2025-04-21T13:00:46Z",
            "iso_date_of_last_edit": "2025-04-21T13:00:46Z",
            "source": "Google",
            "review_id": "ChdDSUhNMG9nS0VJQ0FnTURvOE5LNHZBRRAB",
            "user": {
                "name": "Dayani Sanjeewani",
                "link": "https://www.google.com/maps/contrib/105481924050849444760?hl=en",
                "contributor_id": "105481924050849444760",
                "thumbnail": "https://lh3.googleusercontent.com/a-/ALV-UjUwAnERH9kx2Rn1_17JIHXCFIxxKkA46L-KBhrouUbSgj7wYBFv=s120-c-rp-mo-ba2-br100",
                "local_guide": true,
                "reviews": 8,
                "photos": 36
            },
            "details": {
                "service": 4,
                "meal_type": "Dinner",
                "price_per_person": "\u00a53,000\u20134,000",
                "food": 3,
                "atmosphere": 4,
                "recommended_dishes": "Samosa"
            },
            "response": {
                "date": "3 months ago",
                "iso_date": "2025-04-27T12:20:53Z",
                "iso_date_of_last_edit": "2025-04-27T12:20:53Z",
                "snippet": "Thank you ",
                "extracted_snippet": {
                    "original": "Thank you "
                }
            }
        },
        {
            "link": "https://www.google.com/maps/reviews/data=!4m8!14m7!1m6!2m5!1sChZDSUhNMG9nS0VJQ0FnTUNvanZXRFdnEAE!2m1!1s0x0:0x8fd99463dfe3d9e!3m1!1s2@1:CIHM0ogKEICAgMCojvWDWg%7CCgsInsiBwAYQ4JOfbQ%7C?hl=en",
            "rating": 5.0,
            "date": "3 months ago",
            "iso_date": "2025-04-17T02:14:54Z",
            "iso_date_of_last_edit": "2025-04-17T02:14:54Z",
            "source": "Google",
            "review_id": "ChZDSUhNMG9nS0VJQ0FnTUNvanZXRFdnEAE",
            "user": {
                "name": "didit",
                "link": "https://www.google.com/maps/contrib/113011167091089576122?hl=en",
                "contributor_id": "113011167091089576122",
                "thumbnail": "https://lh3.googleusercontent.com/a-/ALV-UjVyYjpraWa-Sm0oO4cnWcG-Vl0lKPmBX5odfWWXXcl5dFA5GDDS=s120-c-rp-mo-ba5-br100",
                "local_guide": true,
                "reviews": 115,
                "photos": 1065
            },
            "snippet": "All perfect in this restaurant",
            "extracted_snippet": {
                "original": "All perfect in this restaurant"
            },
            "details": {
                "service": 5,
                "price_per_person": "\u00a51,000\u20132,000",
                "food": 5,
                "atmosphere": 5,
                "recommended_dishes": "Yakiniku Bbq"
            },
            "response": {
                "date": "3 months ago",
                "iso_date": "2025-04-18T13:37:01Z",
                "iso_date_of_last_edit": "2025-04-18T13:37:01Z",
                "snippet": "Thank you so much ",
                "extracted_snippet": {
                    "original": "Thank you so much "
                }
            }
        },
        {
            "link": "https://www.google.com/maps/reviews/data=!4m8!14m7!1m6!2m5!1sChZDSUhNMG9nS0VJQ0FnTUNvd01TUVFREAE!2m1!1s0x0:0x8fd99463dfe3d9e!3m1!1s2@1:CIHM0ogKEICAgMCowMSQQQ%7CCgsI2sbyvwYQ0L3BAQ%7C?hl=en",
            "rating": 5.0,
            "date": "3 months ago",
            "iso_date": "2025-04-14T05:55:38Z",
            "iso_date_of_last_edit": "2025-04-14T05:55:38Z",
            "source": "Google",
            "review_id": "ChZDSUhNMG9nS0VJQ0FnTUNvd01TUVFREAE",
            "user": {
                "name": "\u0130sa Tas",
                "link": "https://www.google.com/maps/contrib/106694736903382805270?hl=en",
                "contributor_id": "106694736903382805270",
                "thumbnail": "https://lh3.googleusercontent.com/a-/ALV-UjVtpu_K0VIis50NcerBCPBQ-IyxOfRbDy7tvGRU-qwIrMCFzCg-=s120-c-rp-mo-br100",
                "local_guide": true,
                "reviews": 6,
                "photos": 0
            },
            "snippet": "\u00c7ok lezzetli \ud83d\ude0b\ud83d\ude0b\ud83d\ude0b",
            "extracted_snippet": {
                "original": "\u00c7ok lezzetli \ud83d\ude0b\ud83d\ude0b\ud83d\ude0b",
                "translated": "Very delicious \ud83d\ude0b\ud83d\ude0b\ud83d\ude0b"
            },
            "details": {
                "meal_type": "Lunch",
                "price_per_person": "\u00a51,000\u20132,000",
                "food": 5,
                "service": 5,
                "atmosphere": 4,
                "recommended_dishes": "\u00d6zbek Pilav\u0131"
            },
            "response": {
                "date": "3 months ago",
                "iso_date": "2025-04-14T06:12:29Z",
                "iso_date_of_last_edit": "2025-04-14T06:12:29Z",
                "snippet": "Te\u015fekk\u00fcr ederiz! Afiyet olsun!\nSizi tekrar a\u011f\u0131rlamaktan mutluluk duyar\u0131z!",
                "extracted_snippet": {
                    "original": "Te\u015fekk\u00fcr ederiz! Afiyet olsun!\nSizi tekrar a\u011f\u0131rlamaktan mutluluk duyar\u0131z!",
                    "translated": "Thank you! Enjoy your meal!\nWe would be happy to welcome you again!"
                }
            }
        },
        {
            "link": "https://www.google.com/maps/reviews/data=!4m8!14m7!1m6!2m5!1sChRDSUhNMG9nS0VJQ0FnTURJaDVzbhAB!2m1!1s0x0:0x8fd99463dfe3d9e!3m1!1s2@1:CIHM0ogKEICAgMDIh5sn%7CCgwIgcfuvwYQ2LT2xQE%7C?hl=en",
            "rating": 5.0,
            "date": "3 months ago",
            "iso_date": "2025-04-13T11:44:01Z",
            "iso_date_of_last_edit": "2025-04-13T11:44:01Z",
            "images": [
                "https://lh3.googleusercontent.com/geougc-cs/AB3l90D4qOjUiVFjnS7cRcnUjtH91TSpZsewNInRlrL5WxLjnJ-MQ6cx-eucKz43AWSiDbYOHF97ffCo0q6YGh0ExYkuUtyQYBP2Ft1_6Fdb0cr0eBg9obEg6vqNlNmyP_pUJwZtRvwf",
                "https://lh3.googleusercontent.com/geougc-cs/AB3l90Ci5K1dQvjankivAx6t82hoOfd4L4CJ2qX04KcAuV5yxCK5l511R0e3_tLHput36gi4oSyX8TSNarXmeGpGuL8vvqo_LD0vuWxN7w7gltf4XS1PZsnQkOTpGQJYIxbhhu8VswOzcg",
                "https://lh3.googleusercontent.com/geougc-cs/AB3l90CoY2-r2zFmDUdBGjNvHCpnMrFGAbaPLk5vWxkmRfmM--wZcIAEp5CM57g_R-XSb0UvDc1AupiZFpADUx8vqlrRTcgXSrt4BEvBE68nks-AToHeLoM0aRTQPk-w0pGQTmBHzlYH",
                "https://lh3.googleusercontent.com/geougc-cs/AB3l90BRF49Q-L2d1MOzhcNtcGjn7Fjj_Hau1kOf3yqb3gthNHJAokbQlWPRzb1VZkECmHUpJ1L2ijZ92uX2FeYBVkYDdFCm_VA4fuLPbt2aTlcDJ-pM6X-E8BSr3y_iwiBnsJT1ZXgC",
                "https://lh3.googleusercontent.com/geougc-cs/AB3l90AvL8E-KYhQ1ypTxkSC12Z782VQv9vxFdQNKkAvdDS5nISXZ7XExzgPfDb1q2U5Sk8byWLsn4bfLx9qPRDAh0bOdGmjP7r4S2aWiVU4ehWtGXqBzMGCLsScBrfWpTZBISKbol6M",
                "https://lh3.googleusercontent.com/geougc-cs/AB3l90DM_IS109moP6imiOPwCzvzVn0TH31nCWOeS8--rfj2FIUEfJxQnZKSd6NiWvAlDtoYEMcPTlVkZ257S1i9pnJLD92EKP8RK2P-zMTJzsZJvxYT2fyh8uBr4xkip9-citqkIFIX",
                "https://lh3.googleusercontent.com/geougc-cs/AB3l90CZSfXrKwYft8nlc-wkxWHehd73JUuBpHSeV2zGPgyyJDhS_JqKXxHPAkhsriCpAUjyyL5oHY07MkWJ76O9gcpm7lFwZaIymAEGGLKaB2Tm0ofgtoqgkq0_FkWq4et0V4duYGxO",
                "https://lh3.googleusercontent.com/geougc-cs/AB3l90C_K--qA7VpfWB0CTBz7-WdbmZIkrvPJxkALuyh3cSq7v-w876eIWWDqaqEIJaMb7Rsw953WjIDkuYuWIoKoPgf5jwIh_DIAo7nER_DlhBlUgIC8g8ttAecTPYb8YZOylxU69MA",
                "https://lh3.googleusercontent.com/geougc-cs/AB3l90Dqy20kkGC4iq_j_At8IM6plm-SHXWz7HRYBDFNr49xxArxCTGOssY4iPXBaZtZfhY2pAwy6DhZ85X_KmXOqlD9f_4yUrOk55n3bhmhFVQ3MCEPH0SEa6bcdM1MZeihnQ_BZEkC",
                "https://lh3.googleusercontent.com/geougc-cs/AB3l90BDvzhOAvfCEoEQNAc7l3E865aDantJHDrWidJb5UTRVKTszwZdl4DmS1PPoHYjAGcoUhAQyVFDvCA0Zu7UtnwZYDDB-w9JZik28uLifMPNcehDF-Fs4shG_YYjtCvpUiKBmVFkgg",
                "https://lh3.googleusercontent.com/geougc-cs/AB3l90BEEGgZTbBiBAd6cC_DbXeEXwOxN3MtxMA2O5ohh79KlGrrauuHcqNvDvg9jfR7XyZXEKJeE4ghVXxBEYmcqvPsWFmmD6iwZa6ON3cffVTCtjsJPU8QhmmDcmXXRIQOlHQqjkZx"
            ],
            "source": "Google",
            "review_id": "ChRDSUhNMG9nS0VJQ0FnTURJaDVzbhAB",
            "user": {
                "name": "Heny Setyawati",
                "link": "https://www.google.com/maps/contrib/112975674277993713694?hl=en",
                "contributor_id": "112975674277993713694",
                "thumbnail": "https://lh3.googleusercontent.com/a-/ALV-UjWvJEOSg3SAJbjYo4sHj6Al6QFb6qUoh0Bw3xjk9h0wmqjys7r3XA=s120-c-rp-mo-ba5-br100",
                "local_guide": true,
                "reviews": 138,
                "photos": 432
            },
            "details": {
                "food": 5,
                "service": 5,
                "atmosphere": 5
            },
            "response": {
                "date": "3 months ago",
                "iso_date": "2025-04-14T06:12:52Z",
                "iso_date_of_last_edit": "2025-04-14T06:12:52Z",
                "snippet": "Thank you very much!",
                "extracted_snippet": {
                    "original": "Thank you very much!"
                }
            }
        },
        {
            "link": "https://www.google.com/maps/reviews/data=!4m8!14m7!1m6!2m5!1sChZDSUhNMG9nS0VJQ0FnTURJaU12akVREAE!2m1!1s0x0:0x8fd99463dfe3d9e!3m1!1s2@1:CIHM0ogKEICAgMDIiMvjEQ%7CCgwImKjKvwYQ6Lfe_wE%7C?hl=en",
            "rating": 5.0,
            "date": "4 months ago",
            "iso_date": "2025-04-06T14:47:52Z",
            "iso_date_of_last_edit": "2025-04-06T14:47:52Z",
            "source": "Google",
            "review_id": "ChZDSUhNMG9nS0VJQ0FnTURJaU12akVREAE",
            "user": {
                "name": "Aban Zahid",
                "link": "https://www.google.com/maps/contrib/101191500922199739320?hl=en",
                "contributor_id": "101191500922199739320",
                "thumbnail": "https://lh3.googleusercontent.com/a/ACg8ocJCQj-Tkfg7K5lpQCUz5sfCiWnKJbEBWVpCKdmnW9oGTKQHZA=s120-c-rp-mo-br100",
                "local_guide": true,
                "reviews": 1,
                "photos": 0
            },
            "snippet": "\u5473\u304c\u3068\u3063\u3066\u3082\u7f8e\u5473\u3057\u304f\u5e97\u54e1\u3055\u3093\u306e\u63a5\u5ba2\u614b\u5ea6\u306b\u52aa\u529b\u304c\u611f\u3058\u3089\u308c\u307e\u3059\uff01\u307e\u3042\u4e00\u5ea6\u884c\u304d\u305f\u304f\u306a\u308b\u3088\u3046\u306a\u304a\u5e97\u3067\u3057\u305f\uff01",
            "extracted_snippet": {
                "original": "\u5473\u304c\u3068\u3063\u3066\u3082\u7f8e\u5473\u3057\u304f\u5e97\u54e1\u3055\u3093\u306e\u63a5\u5ba2\u614b\u5ea6\u306b\u52aa\u529b\u304c\u611f\u3058\u3089\u308c\u307e\u3059\uff01\u307e\u3042\u4e00\u5ea6\u884c\u304d\u305f\u304f\u306a\u308b\u3088\u3046\u306a\u304a\u5e97\u3067\u3057\u305f\uff01",
                "translated": "The taste is very delicious and you can feel the effort put into the customer service by the staff! Well, it was a shop that you would want to visit at least once!"
            },
            "details": {
                "service": 5,
                "meal_type": "Lunch",
                "price_per_person": "\u00a53,000\u20134,000",
                "food": 5,
                "atmosphere": 4,
                "recommended_dishes": "\u7f8a\u30b1\u30d0\u30d6\u3068\u9ce5\u30b1\u30d0\u30d6, \u30c9\u30ea\u30f3\u30af, \u30b5\u30e2\u30b5, \u30b1\u30d0\u30d6, \u30b1\u30d0\u30d6\u30e9\u30c3\u30d7\u30d3\u30fc\u30d5 kebab beef wrap"
            },
            "response": {
                "date": "3 months ago",
                "iso_date": "2025-04-09T00:54:51Z",
                "iso_date_of_last_edit": "2025-04-09T00:54:51Z",
                "snippet": "\u3054\u6765\u5e97\u3068\u5b09\u3057\u3044\u53e3\u30b3\u30df\u3092\u3042\u308a\u304c\u3068\u3046\u3054\u3056\u3044\u307e\u3059\uff01\n\u304a\u6599\u7406\u3084\u63a5\u5ba2\u3092\u304a\u8912\u3081\u3044\u305f\u3060\u304d\u3001\u3068\u3066\u3082\u52b1\u307f\u306b\u306a\u308a\u307e\u3059\u3002\n\u307e\u305f\u304a\u4f1a\u3044\u3067\u304d\u308b\u306e\u3092\u30b9\u30bf\u30c3\u30d5\u4e00\u540c\u3001\u5fc3\u3088\u308a\u697d\u3057\u307f\u306b\u3057\u3066\u304a\u308a\u307e\u3059\uff01",
                "extracted_snippet": {
                    "original": "\u3054\u6765\u5e97\u3068\u5b09\u3057\u3044\u53e3\u30b3\u30df\u3092\u3042\u308a\u304c\u3068\u3046\u3054\u3056\u3044\u307e\u3059\uff01\n\u304a\u6599\u7406\u3084\u63a5\u5ba2\u3092\u304a\u8912\u3081\u3044\u305f\u3060\u304d\u3001\u3068\u3066\u3082\u52b1\u307f\u306b\u306a\u308a\u307e\u3059\u3002\n\u307e\u305f\u304a\u4f1a\u3044\u3067\u304d\u308b\u306e\u3092\u30b9\u30bf\u30c3\u30d5\u4e00\u540c\u3001\u5fc3\u3088\u308a\u697d\u3057\u307f\u306b\u3057\u3066\u304a\u308a\u307e\u3059\uff01",
                    "translated": "Thank you for visiting us and for your nice review!\nIt is very encouraging to receive compliments on our food and customer service.\nAll the staff are looking forward to seeing you again!"
                }
            }
        },
        {
            "link": "https://www.google.com/maps/reviews/data=!4m8!14m7!1m6!2m5!1sChZDSUhNMG9nS0VJQ0FnTUNJdDVuZVV3EAE!2m1!1s0x0:0x8fd99463dfe3d9e!3m1!1s2@1:CIHM0ogKEICAgMCIt5neUw%7CCgwImpXEvwYQ8N3SkQI%7C?hl=en",
            "rating": 5.0,
            "date": "4 months ago",
            "iso_date": "2025-04-05T10:48:58Z",
            "iso_date_of_last_edit": "2025-04-05T10:48:58Z",
            "images": [
                "https://lh3.googleusercontent.com/geougc-cs/AB3l90D6V9L-iFVGaqaAGiAi7pKYRKmw9i6gbEggMHT-XveetcAFcn7YiY-S0Gbm63LgdyjN17uma2-kTZ6Ko9TzCr_ng-52EaujPi-6RvUx14Hq9v7mkCRFOhQW1MuOF6pKQbJw8V4RDQ"
            ],
            "source": "Google",
            "review_id": "ChZDSUhNMG9nS0VJQ0FnTUNJdDVuZVV3EAE",
            "user": {
                "name": "Ufuk Temizer",
                "link": "https://www.google.com/maps/contrib/107747380578329615538?hl=en",
                "contributor_id": "107747380578329615538",
                "thumbnail": "https://lh3.googleusercontent.com/a/ACg8ocKIKCmp5TRnloqS6i5SHUFbRZ0ItcqtJnPTmvfTI6BItuUjKA=s120-c-rp-mo-br100",
                "local_guide": true,
                "reviews": 3,
                "photos": 1
            },
            "snippet": "Yemeklerin hepsi s\u0131cak geldi ve \u00e7ok lezzetliydi.Mekan \u00e7ok temizdi.\nJaponya'da \u00d6zbek mutfa\u011f\u0131n\u0131 deneyimlemek i\u00e7in gidebilirsiniz.\u00d6zellikle samsa mutlaka denenmeli.",
            "extracted_snippet": {
                "original": "Yemeklerin hepsi s\u0131cak geldi ve \u00e7ok lezzetliydi.Mekan \u00e7ok temizdi.\nJaponya'da \u00d6zbek mutfa\u011f\u0131n\u0131 deneyimlemek i\u00e7in gidebilirsiniz.\u00d6zellikle samsa mutlaka denenmeli.",
                "translated": "All the food came hot and was very delicious. The place was very clean.\nYou can go to Japan to experience Uzbek cuisine. Especially samsa should definitely be tried."
            },
            "details": {
                "food": 5,
                "service": 5,
                "atmosphere": 5
            },
            "response": {
                "date": "4 months ago",
                "iso_date": "2025-04-06T00:02:31Z",
                "iso_date_of_last_edit": "2025-04-06T00:02:31Z",
                "snippet": "Thank you so much! We\u2019re glad you enjoyed the food and atmosphere. Hope to see you again soon!",
                "extracted_snippet": {
                    "original": "Thank you so much! We\u2019re glad you enjoyed the food and atmosphere. Hope to see you again soon!"
                }
            }
        },
        {
            "link": "https://www.google.com/maps/reviews/data=!4m8!14m7!1m6!2m5!1sChZDSUhNMG9nS0VJQ0FnTUNJbEtHRWJnEAE!2m1!1s0x0:0x8fd99463dfe3d9e!3m1!1s2@1:CIHM0ogKEICAgMCIlKGEbg%7CCgwItaylvwYQ4PzowAM%7C?hl=en",
            "rating": 4.0,
            "date": "4 months ago",
            "iso_date": "2025-03-30T14:33:25Z",
            "iso_date_of_last_edit": "2025-03-30T14:33:25Z",
            "source": "Google",
            "review_id": "ChZDSUhNMG9nS0VJQ0FnTUNJbEtHRWJnEAE",
            "user": {
                "name": "Chaz",
                "link": "https://www.google.com/maps/contrib/108376493175312767383?hl=en",
                "contributor_id": "108376493175312767383",
                "thumbnail": "https://lh3.googleusercontent.com/a-/ALV-UjWCsZXnI3McDqP2uXmsQV8v4BvNThl9FLqDICmCDZUHHvGRpRLN=s120-c-rp-mo-ba5-br100",
                "local_guide": true,
                "reviews": 132,
                "photos": 1175
            },
            "snippet": "Wonderful halal selection and atmosphere",
            "extracted_snippet": {
                "original": "Wonderful halal selection and atmosphere"
            },
            "details": {
                "service": 5,
                "meal_type": "Dinner",
                "price_per_person": "\u00a51,000\u20132,000",
                "food": 4,
                "atmosphere": 5,
                "recommended_dishes": "Beef Ramen, Noodle Soup, Uyghur Hot Pot"
            },
            "response": {
                "date": "4 months ago",
                "iso_date": "2025-03-30T21:44:38Z",
                "iso_date_of_last_edit": "2025-03-30T21:44:38Z",
                "snippet": "Thank you for your kind words! We\u2019re glad you enjoyed our halal selection and atmosphere. We look forward to welcoming you again soon!",
                "extracted_snippet": {
                    "original": "Thank you for your kind words! We\u2019re glad you enjoyed our halal selection and atmosphere. We look forward to welcoming you again soon!"
                }
            }
        },
        {
            "link": "https://www.google.com/maps/reviews/data=!4m8!14m7!1m6!2m5!1sChZDSUhNMG9nS0VJQ0FnTUR3c1picUR3EAE!2m1!1s0x0:0x8fd99463dfe3d9e!3m1!1s2@1:CIHM0ogKEICAgMDwsZbqDw%7CCgwI0L6QvwYQ0M3v1gM%7C?hl=en",
            "rating": 5.0,
            "date": "4 months ago",
            "iso_date": "2025-03-26T15:37:52Z",
            "iso_date_of_last_edit": "2025-03-26T15:37:52Z",
            "source": "Google",
            "review_id": "ChZDSUhNMG9nS0VJQ0FnTUR3c1picUR3EAE",
            "user": {
                "name": "Abduvokhidova Aisha",
                "link": "https://www.google.com/maps/contrib/103973447402612745794?hl=en",
                "contributor_id": "103973447402612745794",
                "thumbnail": "https://lh3.googleusercontent.com/a/ACg8ocL1e25kjxjbnSOHdkT3YO64mnRCaYdY5E0_hRFki6ocESOxGg=s120-c-rp-mo-br100",
                "local_guide": true,
                "reviews": 3,
                "photos": 11
            },
            "response": {
                "date": "4 months ago",
                "iso_date": "2025-03-30T21:45:01Z",
                "iso_date_of_last_edit": "2025-03-30T21:45:01Z",
                "snippet": "Katta rahmat!",
                "extracted_snippet": {
                    "original": "Katta rahmat!",
                    "translated": "Thank you very much!"
                }
            }
        }
    ],
    "serpapi_pagination": {
        "next": "https://serpapi.com/search.json?engine=google_maps_reviews&hl=en&next_page_token=CAESYENBRVFNQnBDUTJrNFNVRlNTVzVEWjI5QlVEY3lSMjl6TldGMWExOWZSV2hEWm5KM1NGbzJjVVJZVHpkdFdYRnBUVUZCUVVGQlIyZG1YMEZ0YjNNMVlYVnJSMEZCYVVGQg%3D%3D&num=20&place_id=ChIJn4ii2YCOGGARnj3-PUaZ_Qg&sort_by=newestFirst",
        "next_page_token": "CAESYENBRVFNQnBDUTJrNFNVRlNTVzVEWjI5QlVEY3lSMjl6TldGMWExOWZSV2hEWm5KM1NGbzJjVVJZVHpkdFdYRnBUVUZCUVVGQlIyZG1YMEZ0YjNNMVlYVnJSMEZCYVVGQg=="
    }
}